analysis_root/__init__.py
analysis_root/__main__.py
sifts/__init__.py
sifts/__main__.py
sifts/py.typed
sifts/analysis/__init__.py
sifts/analysis/agent_analysis.py
sifts/analysis/agent_selector.py
sifts/analysis/code_parser.py
sifts/analysis/constants.py
sifts/analysis/criteria.py
sifts/analysis/criteria_data.py
sifts/analysis/orchestrator.py
sifts/analysis/results_processor.py
sifts/analysis/types.py
sifts/analysis/tools/__init__.py
sifts/analysis/tools/format_response.py
sifts/analysis/tools/fuzzy_matcher.py
sifts/analysis/tools/joern_search.py
sifts/analysis/tools/search_by_id.py
sifts/analysis/tools/search_by_name.py
sifts/cli/__init__.py
sifts/common_types/__init__.py
sifts/common_types/snippets.py
sifts/config/__init__.py
sifts/config/settings.py
sifts/core/__init__.py
sifts/core/parallel_utils.py
sifts/core/reactive_utils.py
sifts/core/repository.py
sifts/core/retry_utils.py
sifts/core/sarif_result.py
sifts/core/types.py
sifts/cpg/__init__.py
sifts/io/__init__.py
sifts/io/api.py
sifts/io/file_system.py
sifts/io/file_system_defaults.py
sifts/io/tar.py
sifts/io/tree.py
sifts/io/aws/__init__.py
sifts/io/db/__init__.py
sifts/io/db/base.py
sifts/io/db/ctags_tinydb.py
sifts/io/db/data_loaders.py
sifts/io/db/dynamodb.py
sifts/io/db/dynamodb_backend.py
sifts/io/db/factory.py
sifts/io/db/memory_vector_db.py
sifts/io/db/opensearch_client.py
sifts/io/db/queries.py
sifts/io/db/sqlite_backend.py
sifts/io/db/types.py
sifts/io/vcs/__init__.py
sifts/io/vcs/git.py
sifts/llm/__init__.py
sifts/llm/bedrock.py
sifts/llm/config_data.py
sifts/llm/constants.py
sifts/llm/fix_code.py
sifts/llm/prompts.py
sifts/llm/propose_changes.py
sifts/llm/ranking.py
sifts/llm/router.py
sifts/llm/tool_definitions.py
sifts/llm/types.py
sifts/llm/usage.py
sifts/llm/vulnerability_assessment.py
sifts/static/model_parameters.yaml
sifts/static/typology_embedding.json
fluidattacks_sifts-0.20.0.dist-info/METADATA
fluidattacks_sifts-0.20.0.dist-info/WHEEL
fluidattacks_sifts-0.20.0.dist-info/entry_points.txt
fluidattacks_sifts-0.20.0.dist-info/top_level.txt
fluidattacks_sifts-0.20.0.dist-info/RECORD
