Metadata-Version: 2.4
Name: fluidattacks-sifts
Version: 0.20.0
Requires-Python: <3.13,>=3.12
Requires-Dist: aioboto3>=15.1.0
Requires-Dist: aiofiles==24.1.0
Requires-Dist: aiosqlite==0.21.0
Requires-Dist: asyncache==0.3.1
Requires-Dist: click>=8.1.8
Requires-Dist: datamodel-code-generator>=0.31.2
Requires-Dist: diskcache==5.6.3
Requires-Dist: fluidattacks-core[serializers]>=2.13.6
Requires-Dist: GitPython==3.1.41
Requires-Dist: litellm==1.71.2
Requires-Dist: more-itertools==10.7.0
Requires-Dist: networkx>=3.5
Requires-Dist: openai>=1.109.1
Requires-Dist: openai-agents>=0.3.2
Requires-Dist: opensearch-py==2.8.0
Requires-Dist: orjson==3.10.18
Requires-Dist: platformdirs==4.3.8
Requires-Dist: pydantic==2.11.5
Requires-Dist: pyyaml==6.0.2
Requires-Dist: reactivex==4.0.4
Requires-Dist: redis==6.2.0
Requires-Dist: sagemaker>=2.247.1
Requires-Dist: sarif-om==1.0.4
Requires-Dist: snowflake-connector-python>=3.17.3
Requires-Dist: snowflake-utils
Requires-Dist: starlette>=0.47.2
Requires-Dist: thefuzz==0.22.1
Requires-Dist: tinydb==4.8.2
Requires-Dist: types-aioboto3[bedrock-runtime,dynamodb,s3,sqs]==14.3.0
Requires-Dist: types-cachetools>=6.0.0.20250525
Requires-Dist: voyageai==0.3.2
